mcp_docker/__init__.py
mcp_docker/__main__.py
mcp_docker/config.py
mcp_docker/py.typed
mcp_docker/version.py
mcp_docker/auth/__init__.py
mcp_docker/auth/models.py
mcp_docker/auth/oauth_auth.py
mcp_docker/docker/__init__.py
mcp_docker/docker/client.py
mcp_docker/middleware/__init__.py
mcp_docker/middleware/audit.py
mcp_docker/middleware/auth.py
mcp_docker/middleware/debug_logging.py
mcp_docker/middleware/error_handler.py
mcp_docker/middleware/rate_limit.py
mcp_docker/middleware/safety.py
mcp_docker/middleware/utils.py
mcp_docker/server/__init__.py
mcp_docker/server/prompts.py
mcp_docker/server/resources.py
mcp_docker/server/server.py
mcp_docker/services/__init__.py
mcp_docker/services/audit.py
mcp_docker/services/rate_limiter.py
mcp_docker/services/safety.py
mcp_docker/services/safety_enforcer.py
mcp_docker/tools/__init__.py
mcp_docker/tools/common.py
mcp_docker/tools/container_inspection.py
mcp_docker/tools/container_lifecycle.py
mcp_docker/tools/filters.py
mcp_docker/tools/image.py
mcp_docker/tools/network.py
mcp_docker/tools/registration.py
mcp_docker/tools/system.py
mcp_docker/tools/volume.py
mcp_docker/utils/__init__.py
mcp_docker/utils/error_sanitizer.py
mcp_docker/utils/errors.py
mcp_docker/utils/fastmcp_helpers.py
mcp_docker/utils/http_helpers.py
mcp_docker/utils/json_parsing.py
mcp_docker/utils/logger.py
mcp_docker/utils/messages.py
mcp_docker/utils/output_limits.py
mcp_docker/utils/stats_formatter.py
mcp_docker/utils/validation.py
mcp_docker-1.2.6.dist-info/METADATA
mcp_docker-1.2.6.dist-info/WHEEL
mcp_docker-1.2.6.dist-info/entry_points.txt
mcp_docker-1.2.6.dist-info/licenses/LICENSE
mcp_docker-1.2.6.dist-info/RECORD
