Metadata-Version: 2.4
Name: mcp-docker
Version: 1.2.6
Summary: Model Context Protocol server for Docker management with AI assistants
Project-URL: Homepage, https://github.com/williajm/mcp_docker
Project-URL: Documentation, https://williajm.github.io/mcp_docker/
Project-URL: Repository, https://github.com/williajm/mcp_docker
Project-URL: PyPI, https://pypi.org/project/mcp-docker/
Project-URL: Issues, https://github.com/williajm/mcp_docker/issues
Project-URL: Changelog, https://github.com/williajm/mcp_docker/releases
Project-URL: Stats, https://pypi.kopdog.com/package/?name=mcp-docker
Author: James Williams
License: MIT
License-File: LICENSE
Keywords: ai,claude,containers,docker,docker-management,llm,mcp,model-context-protocol
Classifier: Development Status :: 5 - Production/Stable
Classifier: Intended Audience :: Developers
Classifier: Intended Audience :: System Administrators
Classifier: License :: OSI Approved :: MIT License
Classifier: Operating System :: OS Independent
Classifier: Programming Language :: Python :: 3
Classifier: Programming Language :: Python :: 3.11
Classifier: Programming Language :: Python :: 3.12
Classifier: Programming Language :: Python :: 3.13
Classifier: Programming Language :: Python :: 3.14
Classifier: Topic :: Software Development :: Libraries :: Python Modules
Classifier: Topic :: System :: Systems Administration
Classifier: Topic :: Utilities
Classifier: Typing :: Typed
Requires-Python: >=3.11
Requires-Dist: authlib>=1.6.6
Requires-Dist: cachetools>=6.2.4
Requires-Dist: docker>=7.1.0
Requires-Dist: fastmcp>=2.14.3
Requires-Dist: httpx>=0.28.1
Requires-Dist: humanfriendly>=10.0
Requires-Dist: limits>=5.6.0
Requires-Dist: loguru>=0.7.3
Requires-Dist: pydantic-settings>=2.12.0
Requires-Dist: pydantic>=2.12.5
Requires-Dist: secure>=1.0.1
Requires-Dist: starlette>=0.50.0
Requires-Dist: typer>=0.20.0
Requires-Dist: uvicorn>=0.38.0
Provides-Extra: dev
Requires-Dist: atheris>=3.0.0; extra == 'dev'
Requires-Dist: httpx-sse>=0.4.3; extra == 'dev'
Requires-Dist: httpx>=0.28.1; extra == 'dev'
Requires-Dist: hypothesis>=6.148.7; extra == 'dev'
Requires-Dist: mypy>=1.19.1; extra == 'dev'
Requires-Dist: pytest-asyncio>=1.3.0; extra == 'dev'
Requires-Dist: pytest-cov>=7.0.0; extra == 'dev'
Requires-Dist: pytest-docker>=3.2.5; extra == 'dev'
Requires-Dist: pytest>=9.0.2; extra == 'dev'
Requires-Dist: ruff>=0.14.9; extra == 'dev'
Requires-Dist: types-docker>=7.1.0; extra == 'dev'
